{
  "$schema": "http://cyclonedx.org/schema/bom-1.4.schema.json",
  "bomFormat": "CycloneDX",
  "specVersion": "1.4",
  "serialNumber": "urn:uuid:77ab0749-b330-4d7b-9350-719a8cac7ab5",
  "version": 1,
  "metadata": {
    "timestamp": "2023-03-20T23:58:08.784654+00:00",
    "tools": [
      {
        "vendor": "CycloneDX",
        "name": "cyclonedx-bom",
        "version": "3.11.0"
      },
      {
        "vendor": "CycloneDX",
        "name": "cyclonedx-python-lib",
        "version": "3.1.1",
        "externalReferences": [
          {
            "url": "https://github.com/CycloneDX/cyclonedx-python-lib/actions",
            "type": "build-system"
          },
          {
            "url": "https://pypi.org/project/cyclonedx-python-lib/",
            "type": "distribution"
          },
          {
            "url": "https://cyclonedx.github.io/cyclonedx-python-lib/",
            "type": "documentation"
          },
          {
            "url": "https://github.com/CycloneDX/cyclonedx-python-lib/issues",
            "type": "issue-tracker"
          },
          {
            "url": "https://github.com/CycloneDX/cyclonedx-python-lib/blob/main/LICENSE",
            "type": "license"
          },
          {
            "url": "https://github.com/CycloneDX/cyclonedx-python-lib/blob/main/CHANGELOG.md",
            "type": "release-notes"
          },
          {
            "url": "https://github.com/CycloneDX/cyclonedx-python-lib",
            "type": "vcs"
          },
          {
            "url": "https://cyclonedx.org",
            "type": "website"
          }
        ]
      }
    ]
  },
  "components": [
    {
      "type": "library",
      "bom-ref": "bc547981-3f5c-4bf9-8f67-83ab89666fc7",
      "name": "GitPython",
      "version": "3.1.30",
      "purl": "pkg:pypi/gitpython@3.1.30"
    },
    {
      "type": "library",
      "bom-ref": "106595ac-1f13-49a3-abd7-f3019f5f572f",
      "name": "PyYAML",
      "version": "6.0",
      "purl": "pkg:pypi/pyyaml@6.0"
    },
    {
      "type": "library",
      "bom-ref": "67dde6da-c979-4a24-8dd7-d8581a1fcc52",
      "name": "typer",
      "version": "0.7.0",
      "purl": "pkg:pypi/typer@0.7.0"
    }
  ],
  "dependencies": [
    {
      "ref": "bc547981-3f5c-4bf9-8f67-83ab89666fc7",
      "dependsOn": []
    },
    {
      "ref": "106595ac-1f13-49a3-abd7-f3019f5f572f",
      "dependsOn": []
    },
    {
      "ref": "67dde6da-c979-4a24-8dd7-d8581a1fcc52",
      "dependsOn": []
    }
  ]
}
