{
  "$schema": "http://cyclonedx.org/schema/bom-1.4.schema.json",
  "bomFormat": "CycloneDX",
  "specVersion": "1.4",
  "serialNumber": "urn:uuid:38105b24-e4fb-4465-894d-dd3fce6f6c26",
  "version": 1,
  "metadata": {
    "timestamp": "2023-08-16T06:41:21.275347+00:00",
    "tools": [
      {
        "vendor": "CycloneDX",
        "name": "cyclonedx-bom",
        "version": "3.11.2"
      },
      {
        "vendor": "CycloneDX",
        "name": "cyclonedx-python-lib",
        "version": "3.1.5",
        "externalReferences": [
          {
            "url": "https://github.com/CycloneDX/cyclonedx-python-lib/actions",
            "type": "build-system"
          },
          {
            "url": "https://pypi.org/project/cyclonedx-python-lib/",
            "type": "distribution"
          },
          {
            "url": "https://cyclonedx.github.io/cyclonedx-python-lib/",
            "type": "documentation"
          },
          {
            "url": "https://github.com/CycloneDX/cyclonedx-python-lib/issues",
            "type": "issue-tracker"
          },
          {
            "url": "https://github.com/CycloneDX/cyclonedx-python-lib/blob/main/LICENSE",
            "type": "license"
          },
          {
            "url": "https://github.com/CycloneDX/cyclonedx-python-lib/blob/main/CHANGELOG.md",
            "type": "release-notes"
          },
          {
            "url": "https://github.com/CycloneDX/cyclonedx-python-lib",
            "type": "vcs"
          },
          {
            "url": "https://cyclonedx.org",
            "type": "website"
          }
        ]
      }
    ]
  },
  "components": [
    {
      "type": "library",
      "bom-ref": "4742ecfa-5ba9-48d8-8bb5-ab17dc2e262c",
      "name": "GitPython",
      "version": "3.1.32",
      "purl": "pkg:pypi/gitpython@3.1.32"
    },
    {
      "type": "library",
      "bom-ref": "28928099-dc1d-40c5-973d-2f6b5e114a7d",
      "name": "PyYAML",
      "version": "6.0.1",
      "purl": "pkg:pypi/pyyaml@6.0.1"
    },
    {
      "type": "library",
      "bom-ref": "17badf47-d247-4650-bf4f-30e48c802621",
      "name": "dulwich",
      "version": "0.21.5",
      "purl": "pkg:pypi/dulwich@0.21.5"
    },
    {
      "type": "library",
      "bom-ref": "b7e759bb-068a-491a-8618-cbc7d32b0fdb",
      "name": "typer",
      "version": "0.9.0",
      "purl": "pkg:pypi/typer@0.9.0"
    }
  ],
  "dependencies": [
    {
      "ref": "4742ecfa-5ba9-48d8-8bb5-ab17dc2e262c",
      "dependsOn": []
    },
    {
      "ref": "28928099-dc1d-40c5-973d-2f6b5e114a7d",
      "dependsOn": []
    },
    {
      "ref": "17badf47-d247-4650-bf4f-30e48c802621",
      "dependsOn": []
    },
    {
      "ref": "b7e759bb-068a-491a-8618-cbc7d32b0fdb",
      "dependsOn": []
    }
  ]
}
